<?xml version="1.0" ?>
<voe:VOEvent xmlns:xsi="http://www.w3.org/2001/XMLSchema-instance"
xmlns:voe="http://www.ivoa.net/xml/VOEvent/v2.0"
xsi:schemaLocation="http://www.ivoa.net/xml/VOEvent/v2.0 http://www.ivoa.net/xml/VOEvent/VOEvent-v2.0.xsd"
>
    <Table name="data">
        <Description>The datas of GWAlert</Description>
        <Field dataType="int" ucd=""' name="grid_id"' unit="">
            <Description>ID of the grid of fov</Description>
        </Field>
        <Field dataType="int" ucd=""' name="field_id"' unit="">
            <Description>ID of the filed</Description>
        </Field>
        <Field dataType="float" ucd="pos.eq.ra "' name="ra"' unit="deg">
            <Description>The right ascension at center of fov in equatorial coordinates</Description>
        </Field>
        <Field dataType="float" ucd="pos.eq.dec "' name="dec"' unit="deg">
            <Description>The declination at center of fov in equatorial coordinates</Description>
        </Field>
        <Field dataType="float" ucd=" "' name="ra_width"' unit="deg">
            <Description>Width in RA of the fov</Description>
        </Field>
        <Field dataType="float" ucd=""' name="dec_width"' unit="deg">
            <Description>Width in Dec of the fov</Description>
        </Field>
        <Field dataType="float" ucd=""' name="prob_sum"' unit="None">
            <Description>The sum of all pixels in the fov</Description>
        </Field>
        <Field dataType="float" ucd=""' name="observ_time"' unit="sec">
            <Description>Tile mid. observation time in MJD</Description>
        </Field>
        <Field dataType="float" ucd=""' name="airmass"' unit="None">
            <Description>Airmass of tile at mid. observation time</Description>
        </Field>
        <Field dataType="int" ucd=""' name="priority"' unit="">
            <Description></Description>
        </Field>
        <Data>
            <TR>
                <TD>0</TD>
                <TD>672.0</TD>
                <TD>188.32336</TD>
                <TD>33.35</TD>
                <TD>6.86</TD>
                <TD>6.86</TD>
                <TD>0.0091858059939974</TD>
                <TD>55962.26610077188</TD>
                <TD>2.059034635484021</TD>
                <TD>0</TD>
            </TR>
            <TR>
                <TD>0</TD>
                <TD>625.0</TD>
                <TD>188.50914</TD>
                <TD>26.15</TD>
                <TD>6.86</TD>
                <TD>6.86</TD>
                <TD>0.038411867476778716</TD>
                <TD>55962.27686466077</TD>
                <TD>2.0591839763343227</TD>
                <TD>1</TD>
            </TR>
            <TR>
                <TD>0</TD>
                <TD>1670.0</TD>
                <TD>192.25</TD>
                <TD>29.75</TD>
                <TD>6.86</TD>
                <TD>6.86</TD>
                <TD>0.004416904516420281</TD>
                <TD>55962.2840405867</TD>
                <TD>2.0226267802029447</TD>
                <TD>2</TD>
            </TR>
            <TR>
                <TD>0</TD>
                <TD>673.0</TD>
                <TD>196.17664</TD>
                <TD>33.35</TD>
                <TD>6.86</TD>
                <TD>6.86</TD>
                <TD>0.16779341105558293</TD>
                <TD>55962.29121651263</TD>
                <TD>2.000094495984335</TD>
                <TD>3</TD>
            </TR>
            <TR>
                <TD>0</TD>
                <TD>717.0</TD>
                <TD>200.86681</TD>
                <TD>40.55</TD>
                <TD>6.86</TD>
                <TD>6.86</TD>
                <TD>0.007840149614331377</TD>
                <TD>55962.2948044756</TD>
                <TD>1.9958236221997985</TD>
                <TD>4</TD>
            </TR>
            <TR>
                <TD>0</TD>
                <TD>1716.0</TD>
                <TD>204.79978</TD>
                <TD>36.95</TD>
                <TD>6.86</TD>
                <TD>6.86</TD>
                <TD>0.031945382692143594</TD>
                <TD>55962.30915632746</TD>
                <TD>2.0174361307812</TD>
                <TD>5</TD>
            </TR>
            <TR>
                <TD>0</TD>
                <TD>674.0</TD>
                <TD>204.02993</TD>
                <TD>33.35</TD>
                <TD>6.86</TD>
                <TD>6.86</TD>
                <TD>0.2525264333721542</TD>
                <TD>55962.31274429042</TD>
                <TD>2.003552151597323</TD>
                <TD>6</TD>
            </TR>
            <TR>
                <TD>0</TD>
                <TD>718.0</TD>
                <TD>209.48363</TD>
                <TD>40.55</TD>
                <TD>6.86</TD>
                <TD>6.86</TD>
                <TD>0.1089233161728387</TD>
                <TD>55962.31633225339</TD>
                <TD>2.032437700871653</TD>
                <TD>7</TD>
            </TR>
            <TR>
                <TD>0</TD>
                <TD>1717.0</TD>
                <TD>213.1663</TD>
                <TD>36.95</TD>
                <TD>6.86</TD>
                <TD>6.86</TD>
                <TD>0.02870098770531962</TD>
                <TD>55962.33068410525</TD>
                <TD>2.044746105274749</TD>
                <TD>8</TD>
            </TR>
            <TR>
                <TD>0</TD>
                <TD>675.0</TD>
                <TD>211.88321</TD>
                <TD>33.35</TD>
                <TD>6.86</TD>
                <TD>6.86</TD>
                <TD>0.06341698279639643</TD>
                <TD>55962.33427206821</TD>
                <TD>2.007008689313791</TD>
                <TD>9</TD>
            </TR>
            <TR>
                <TD>0</TD>
                <TD>719.0</TD>
                <TD>218.10044</TD>
                <TD>40.55</TD>
                <TD>6.86</TD>
                <TD>6.86</TD>
                <TD>0.027479271085757054</TD>
                <TD>55962.34144799414</TD>
                <TD>2.012038806205854</TD>
                <TD>10</TD>
            </TR>
            <TR>
                <TD>0</TD>
                <TD>676.0</TD>
                <TD>219.7365</TD>
                <TD>33.35</TD>
                <TD>6.86</TD>
                <TD>6.86</TD>
                <TD>0.014369351050982975</TD>
                <TD>55962.355799846</TD>
                <TD>2.010472398625576</TD>
                <TD>11</TD>
            </TR>
            <TR>
                <TD>0</TD>
                <TD>678.0</TD>
                <TD>235.44307</TD>
                <TD>33.35</TD>
                <TD>6.86</TD>
                <TD>6.86</TD>
                <TD>0.061528548845172025</TD>
                <TD>55962.39885540158</TD>
                <TD>2.017449952408852</TD>
                <TD>12</TD>
            </TR>
            <TR>
                <TD>0</TD>
                <TD>1676.0</TD>
                <TD>238.207</TD>
                <TD>29.75</TD>
                <TD>6.86</TD>
                <TD>6.86</TD>
                <TD>0.015631497381002116</TD>
                <TD>55962.409619290476</TD>
                <TD>2.0516354264738976</TD>
                <TD>13</TD>
            </TR>
            <TR>
                <TD>0</TD>
                <TD>679.0</TD>
                <TD>243.29636</TD>
                <TD>33.35</TD>
                <TD>6.86</TD>
                <TD>6.86</TD>
                <TD>0.015346790398713886</TD>
                <TD>55962.42038317937</TD>
                <TD>2.020979657184923</TD>
                <TD>14</TD>
            </TR>
            <TR>
                <TD>0</TD>
                <TD>632.0</TD>
                <TD>240.88114</TD>
                <TD>26.15</TD>
                <TD>6.86</TD>
                <TD>6.86</TD>
                <TD>0.10387283139236284</TD>
                <TD>55962.423971142336</TD>
                <TD>2.0191443776435953</TD>
                <TD>15</TD>
            </TR>
            <TR>
                <TD>0</TD>
                <TD>633.0</TD>
                <TD>248.36286</TD>
                <TD>26.15</TD>
                <TD>6.86</TD>
                <TD>6.86</TD>
                <TD>0.007799238763766022</TD>
                <TD>55962.445498920126</TD>
                <TD>2.0043754681664265</TD>
                <TD>16</TD>
            </TR>
            <TR>
                <TD>0</TD>
                <TD>674.0</TD>
                <TD>204.02993</TD>
                <TD>33.35</TD>
                <TD>6.86</TD>
                <TD>6.86</TD>
                <TD>0.2525264333721542</TD>
                <TD>55962.44619336457</TD>
                <TD>1.0724286886716992</TD>
                <TD>17</TD>
            </TR>
            <TR>
                <TD>0</TD>
                <TD>673.0</TD>
                <TD>196.17664</TD>
                <TD>33.35</TD>
                <TD>6.86</TD>
                <TD>6.86</TD>
                <TD>0.16779341105558293</TD>
                <TD>55962.44978132754</TD>
                <TD>1.028754685975243</TD>
                <TD>18</TD>
            </TR>
            <TR>
                <TD>0</TD>
                <TD>718.0</TD>
                <TD>209.48363</TD>
                <TD>40.55</TD>
                <TD>6.86</TD>
                <TD>6.86</TD>
                <TD>0.1089233161728387</TD>
                <TD>55962.4533692905</TD>
                <TD>1.0910467462964846</TD>
                <TD>19</TD>
            </TR>
            <TR>
                <TD>0</TD>
                <TD>632.0</TD>
                <TD>240.88114</TD>
                <TD>26.15</TD>
                <TD>6.86</TD>
                <TD>6.86</TD>
                <TD>0.10387283139236284</TD>
                <TD>55962.45695725347</TD>
                <TD>1.5736337161368956</TD>
                <TD>20</TD>
            </TR>
            <TR>
                <TD>0</TD>
                <TD>675.0</TD>
                <TD>211.88321</TD>
                <TD>33.35</TD>
                <TD>6.86</TD>
                <TD>6.86</TD>
                <TD>0.06341698279639643</TD>
                <TD>55962.46054521643</TD>
                <TD>1.0895040579445627</TD>
                <TD>21</TD>
            </TR>
            <TR>
                <TD>0</TD>
                <TD>678.0</TD>
                <TD>235.44307</TD>
                <TD>33.35</TD>
                <TD>6.86</TD>
                <TD>6.86</TD>
                <TD>0.061528548845172025</TD>
                <TD>55962.4641331794</TD>
                <TD>1.3375648797637836</TD>
                <TD>22</TD>
            </TR>
            <TR>
                <TD>0</TD>
                <TD>625.0</TD>
                <TD>188.50914</TD>
                <TD>26.15</TD>
                <TD>6.86</TD>
                <TD>6.86</TD>
                <TD>0.038411867476778716</TD>
                <TD>55962.46772114236</TD>
                <TD>1.0086501534337198</TD>
                <TD>23</TD>
            </TR>
            <TR>
                <TD>0</TD>
                <TD>1716.0</TD>
                <TD>204.79978</TD>
                <TD>36.95</TD>
                <TD>6.86</TD>
                <TD>6.86</TD>
                <TD>0.031945382692143594</TD>
                <TD>55962.47130910533</TD>
                <TD>1.0324758122418296</TD>
                <TD>24</TD>
            </TR>
            <TR>
                <TD>0</TD>
                <TD>1717.0</TD>
                <TD>213.1663</TD>
                <TD>36.95</TD>
                <TD>6.86</TD>
                <TD>6.86</TD>
                <TD>0.02870098770531962</TD>
                <TD>55962.47489706829</TD>
                <TD>1.0643626568336895</TD>
                <TD>25</TD>
            </TR>
            <TR>
                <TD>0</TD>
                <TD>719.0</TD>
                <TD>218.10044</TD>
                <TD>40.55</TD>
                <TD>6.86</TD>
                <TD>6.86</TD>
                <TD>0.027479271085757054</TD>
                <TD>55962.47848503126</TD>
                <TD>1.0882206101455145</TD>
                <TD>26</TD>
            </TR>
            <TR>
                <TD>0</TD>
                <TD>1676.0</TD>
                <TD>238.207</TD>
                <TD>29.75</TD>
                <TD>6.86</TD>
                <TD>6.86</TD>
                <TD>0.015631497381002116</TD>
                <TD>55962.48207299422</TD>
                <TD>1.2972847265059737</TD>
                <TD>27</TD>
            </TR>
            <TR>
                <TD>0</TD>
                <TD>679.0</TD>
                <TD>243.29636</TD>
                <TD>33.35</TD>
                <TD>6.86</TD>
                <TD>6.86</TD>
                <TD>0.015346790398713886</TD>
                <TD>55962.48566095719</TD>
                <TD>1.3388332864640697</TD>
                <TD>28</TD>
            </TR>
            <TR>
                <TD>0</TD>
                <TD>676.0</TD>
                <TD>219.7365</TD>
                <TD>33.35</TD>
                <TD>6.86</TD>
                <TD>6.86</TD>
                <TD>0.014369351050982975</TD>
                <TD>55962.48924892015</TD>
                <TD>1.0733360495977713</TD>
                <TD>29</TD>
            </TR>
            <TR>
                <TD>0</TD>
                <TD>672.0</TD>
                <TD>188.32336</TD>
                <TD>33.35</TD>
                <TD>6.86</TD>
                <TD>6.86</TD>
                <TD>0.0091858059939974</TD>
                <TD>55962.49283688312</TD>
                <TD>1.0054197534355849</TD>
                <TD>30</TD>
            </TR>
            <TR>
                <TD>0</TD>
                <TD>717.0</TD>
                <TD>200.86681</TD>
                <TD>40.55</TD>
                <TD>6.86</TD>
                <TD>6.86</TD>
                <TD>0.007840149614331377</TD>
                <TD>55962.49642484608</TD>
                <TD>1.009443004344027</TD>
                <TD>31</TD>
            </TR>
            <TR>
                <TD>0</TD>
                <TD>633.0</TD>
                <TD>248.36286</TD>
                <TD>26.15</TD>
                <TD>6.86</TD>
                <TD>6.86</TD>
                <TD>0.007799238763766022</TD>
                <TD>55962.50001280905</TD>
                <TD>1.3866118485441101</TD>
                <TD>32</TD>
            </TR>
            <TR>
                <TD>0</TD>
                <TD>1670.0</TD>
                <TD>192.25</TD>
                <TD>29.75</TD>
                <TD>6.86</TD>
                <TD>6.86</TD>
                <TD>0.004416904516420281</TD>
                <TD>55962.50360077201</TD>
                <TD>1.0076577361522454</TD>
                <TD>33</TD>
            </TR>
        </Data>
    </Table>
</voe:VOEvent>
